florida/__init__.py
florida/parsing.py
william/__init__.py
william/parsing.py
florida-0.0.6.dist-info/METADATA
florida-0.0.6.dist-info/WHEEL
florida-0.0.6.dist-info/top_level.txt
florida-0.0.6.dist-info/RECORD
