Metadata-Version: 2.1
Name: florida
Version: 0.0.6
Summary: A collection of Python utilities to simplify coding tasks
Home-page: https://github.com/wjbmattingly/florida
Author: WJB Mattingly
Keywords: python utilities tools
Classifier: Development Status :: 3 - Alpha
Classifier: Intended Audience :: Developers
Classifier: License :: OSI Approved :: MIT License
Classifier: Programming Language :: Python :: 3
Classifier: Programming Language :: Python :: 3.7
Classifier: Programming Language :: Python :: 3.8
Classifier: Programming Language :: Python :: 3.9
Classifier: Programming Language :: Python :: 3.10
Classifier: Operating System :: OS Independent
Requires-Python: >=3.7
